easymore/__init__.py
easymore/remapper.py
easymore/scripts/__init__.py
easymore/scripts/_cli_args.py
easymore/scripts/_cli_options.py
easymore/scripts/_conf_args.py
easymore/scripts/_conf_options.py
easymore/scripts/_submit_args.py
easymore/scripts/_submit_options.py
easymore/scripts/main.py
easymore/scripts/assets/default.slurm
easymore-2.0.0.dist-info/LICENSE
easymore-2.0.0.dist-info/METADATA
easymore-2.0.0.dist-info/WHEEL
easymore-2.0.0.dist-info/entry_points.txt
easymore-2.0.0.dist-info/top_level.txt
easymore-2.0.0.dist-info/RECORD
