Metadata-Version: 2.1
Name: easymore
Version: 2.0.0
Summary: geo-spatial processing of the input data for environmental and hydrological modeling
Home-page: https://github.com/ShervanGharari/EASYMORE
Author: Shervan Gharari
Author-email: sh.gharari@gmail.com
License: GPLv3
Keywords: remapping,NetCDF,shapefile,geo-spatial processing,environmental modeling
Platform: any
Classifier: Programming Language :: Python
Classifier: Programming Language :: Python :: 3
Classifier: Programming Language :: Python :: 3.6
Classifier: Programming Language :: Python :: 3.7
Classifier: Programming Language :: Python :: 3.8
Classifier: Programming Language :: Python :: 3.9
Classifier: Natural Language :: English
Classifier: Intended Audience :: Developers
Classifier: Operating System :: OS Independent
Classifier: Topic :: Software Development :: Libraries :: Python Modules
License-File: LICENSE
Requires-Dist: numpy
Requires-Dist: xarray
Requires-Dist: pandas
Requires-Dist: netCDF4
Requires-Dist: datetime
Requires-Dist: cftime
Requires-Dist: geopandas
Requires-Dist: shapely
Requires-Dist: geovoronoi
Requires-Dist: json5
Requires-Dist: matplotlib
Requires-Dist: rtree
Requires-Dist: click
